evolution-simulator/__main__.py
evolution-simulator/configs/automatic_testing/mice_and_owls.ini
evolution-simulator/configs/automatic_testing/my_config.ini
evolution-simulator/configs/automatic_testing/only_mice.ini
evolution-simulator/configs/automatic_testing/run_16_07_20.ini
evolution-simulator/configs/interactive/hello.ini
evolution-simulator/configs/interactive/mice_and_owls.ini
evolution-simulator/configs/interactive/only_mice.ini
evolution-simulator/configs/interactive/smaller_mice_and_owls.ini
evolution-simulator/resources/welcome_text.html
evolution-simulator/src/animals.py
evolution-simulator/src/automatic_testing.py
evolution-simulator/src/data_analyzer.py
evolution-simulator/src/data_grouper.py
evolution-simulator/src/environment.py
evolution-simulator/src/interactive.py
evolution-simulator/src/interactive_graphics.py
evolution-simulator/src/my_plot.pdf
evolution-simulator/src/__pycache__/animals.cpython-37.pyc
evolution-simulator/src/__pycache__/environment.cpython-37.pyc
src/animals.py
src/automatic_testing.py
src/data_analyzer.py
src/data_grouper.py
src/environment.py
src/interactive.py
src/interactive_graphics.py
evolution_simulator-0.1.6.dist-info/METADATA
evolution_simulator-0.1.6.dist-info/WHEEL
evolution_simulator-0.1.6.dist-info/entry_points.txt
evolution_simulator-0.1.6.dist-info/top_level.txt
evolution_simulator-0.1.6.dist-info/RECORD
